moodle_api/Moodle.py
moodle_api/__init__.py
moodle_api/__main__.py
moodle_api/activity/Activity.py
moodle_api/activity/LTIActivity.py
moodle_api/activity/ResourceActivity.py
moodle_api/activity/ResourceFile.py
moodle_api/activity/ResourceList.py
moodle_api/activity/__init__.py
moodle_api/assignment/Assignment.py
moodle_api/assignment/Submission.py
moodle_api/assignment/SubmissionFile.py
moodle_api/assignment/__init__.py
moodle_api/error/MoodleError.py
moodle_api/error/MoodleLoginError.py
moodle_api/error/MoodleParseError.py
moodle_api/error/MoodleUpdateError.py
moodle_api/error/__init__.py
moodle_api/util/LimitedSession.py
moodle_api/util/RequestLimiter.py
moodle_api/util/__init__.py
moodle_api/util/lti/Stage.py
moodle_api/util/lti/__init__.py
moodle_api/util/lti/action/NBGitPuller.py
moodle_api/util/lti/action/__init__.py
moodle_api/util/lti/application/Application.py
moodle_api/util/lti/application/JupyterLab.py
moodle_api/util/lti/application/NBClassic.py
moodle_api/util/lti/application/VSCode.py
moodle_api/util/lti/application/__init__.py
moodle_api/util/lti/spawner/DockerSpawner.py
moodle_api/util/lti/spawner/Spawner.py
moodle_api/util/lti/spawner/__init__.py
moodle_api/util/lti/targets/JupyterHub.py
moodle_api/util/lti/targets/__init__.py
tui_moodle_api-0.1.8.dist-info/METADATA
tui_moodle_api-0.1.8.dist-info/WHEEL
tui_moodle_api-0.1.8.dist-info/top_level.txt
tui_moodle_api-0.1.8.dist-info/RECORD
