Metadata-Version: 2.4
Name: tui-moodle-api
Version: 0.1.8
Summary: scraper for moodle
Home-page: https://dbgit.prakinf.tu-ilmenau.de/ertr8623/moodle-api
Author: Eric Tröbs
Author-email: eric.troebs@tu-ilmenau.de
Project-URL: Bug Tracker, https://dbgit.prakinf.tu-ilmenau.de/ertr8623/moodle-api/issues
Classifier: Programming Language :: Python :: 3
Classifier: License :: OSI Approved :: MIT License
Classifier: Operating System :: OS Independent
Requires-Python: >=3.10
Requires-Dist: aiohttp~=3.11.16
Requires-Dist: beautifulsoup4~=4.13.3
Requires-Dist: pyyaml~=6.0.2
Dynamic: author
Dynamic: author-email
Dynamic: classifier
Dynamic: description-content-type
Dynamic: home-page
Dynamic: project-url
Dynamic: requires-dist
Dynamic: requires-python
Dynamic: summary
